{
  "users": [
    {
      "firstName": "Olena Rymska",
      "lastName": "Violettt",
      "email": "olena.viola@gmail.com",
      "phone": "++380122334561",
      "dateOfBirth": "03/05/1986",
      "id": "e72e92fc-4d20-11eb-ae93-0242ac130002",
      "card": "4242"
    },
    {
      "firstName": "Rudolf dfgdf",
      "lastName": "Grenmakrr",
      "email": "ruddudtut@gmail.com",
      "phone": "+++380123562312",
      "dateOfBirth": "18/12/1882",
      "id": "e72e990a-4d20-11eb-ae93-0242ac130002",
      "card": "4242"
    },
    {
      "firstName": "Rudolf dsfs",
      "lastName": "Grenmakrr sdfsd",
      "email": "ruddudtut@gmail.com",
      "phone": "++380123562312",
      "dateOfBirth": "18/12/1882",
      "id": "e72e9a4a-4d20-11eb-ae93-0242ac130002",
      "card": "4242"
    },
    {
      "firstName": "Zoe",
      "lastName": "Loren",
      "email": "zolo@gmail.com",
      "phone": "+380483946893",
      "dateOfBirth": "12/04/1992",
      "id": "e72e9b26-4d20-11eb-ae93-0242ac130002"
    },
    {
      "firstName": "Robert ds f",
      "lastName": "Brown dfg dferw",
      "email": "robbro@gmail.com",
      "phone": "++38032456789",
      "dateOfBirth": "11/10/1984",
      "id": "e72e9cac-4d20-11eb-ae93-0242ac130002",
      "card": "4242"
    },
    {
      "firstName": "Christopher",
      "lastName": "A. Gray",
      "email": "willjo@gmail.com",
      "phone": "+380408853411",
      "dateOfBirth": "16/08/1976",
      "id": "e72e9ff4-4d20-11eb-ae93-0242ac130002"
    },
    {
      "firstName": "Pamela",
      "lastName": "J. Walton",
      "email": "amelaJWalton@tolo.com ",
      "phone": "+380346789456",
      "dateOfBirth": "22/07/1896",
      "id": "e72ea0bc-4d20-11eb-ae93-0242ac130002"
    },
    {
      "firstName": "Aaliyah",
      "lastName": "Hayesg",
      "email": "AaliyahHayes@dayrep.com",
      "phone": "++380890678456",
      "dateOfBirth": "29/06/1982",
      "id": "e72ea17a-4d20-11eb-ae93-0242ac130002",
      "card": ""
    },
    {
      "firstName": "Corey",
      "lastName": "Arnold",
      "email": "coArnl@gmail.com",
      "phone": "+380483996893",
      "dateOfBirth": "23/04/1984",
      "id": "e72ea2f6-4d20-11eb-ae93-0242ac130002"
    },
    {
      "firstName": "Daisy",
      "lastName": "Benson",
      "email": "DeiBei@gmail.com",
      "phone": "+380503940960",
      "dateOfBirth": "15/08/1884",
      "id": "e72ea3b4-4d20-11eb-ae93-0242ac130002"
    },
    {
      "firstName": "Joe",
      "lastName": "Faulkner",
      "email": "joef@gmail.com",
      "phone": "+380324557094",
      "dateOfBirth": "30/10/1982",
      "id": "e72ea472-4d20-11eb-ae93-0242ac130002"
    },
    {
      "firstName": "Véronique",
      "lastName": "Leduc",
      "email": "veleduc@gmail.com",
      "phone": "+380430623956",
      "dateOfBirth": "26/02/1987",
      "id": "e72ea6f2-4d20-11eb-ae93-0242ac130002"
    },
    {
      "firstName": "Maslin",
      "lastName": "Blondlot",
      "email": "blom@gmail.com",
      "phone": "+380406795341",
      "dateOfBirth": "06/09/1986",
      "id": "e72ea7c4-4d20-11eb-ae93-0242ac130002"
    },
    {
      "firstName": "Amber",
      "lastName": "Renaud",
      "email": "Ambern@tolo.com",
      "phone": "+380378689456",
      "dateOfBirth": "28/04/1982",
      "id": "e72ea878-4d20-11eb-ae93-0242ac130002"
    },
    {
      "firstName": "Test Name gg",
      "lastName": "Last Name gg",
      "email": "dfgdfgfdgdfg@gmail.com",
      "phone": "+0939477574",
      "dateOfBirth": "28/12/2020",
      "id": "_1iYhKb"
    },
    {
      "firstName": "Test Name 9",
      "lastName": "Last name user 5",
      "email": "ertertert@gmail.com",
      "phone": "+15454645654",
      "dateOfBirth": "18/12/1994",
      "id": "nA0F5NR"
    },
    {
      "firstName": "Ira ",
      "lastName": "Lat name 2",
      "email": "fsdfsd@gmail.com",
      "phone": "+998435435345",
      "dateOfBirth": "30/12/1996",
      "id": "9Efgfg"
    },
    {
      "firstName": "Ira sdfsdf",
      "lastName": "Lat ffffname 2",
      "email": "fsdfdfdsfsd@gmail.com",
      "phone": "+998435435345",
      "dateOfBirth": "30/12/1996",
      "id": "9tyty"
    },
    {
      "firstName": "Ira ewrewr",
      "lastName": "Lat name g",
      "email": "adsfsdafsd@gmail.com",
      "phone": "+998435435345",
      "dateOfBirth": "30/12/1996",
      "id": "9cvbcvbcv"
    },
    {
      "firstName": "Ira cvbvcc",
      "lastName": "Lat name 68",
      "email": "fcvbdsfdsfbcv@gmail.com",
      "phone": "+998435435345",
      "dateOfBirth": "30/12/1996",
      "id": "10zdfggfg"
    },
    {
      "firstName": "Ira uyiuyiuy",
      "lastName": "Lat dsfsdfsd",
      "email": "fcdsfdsfcvbcv@gmail.com",
      "phone": "+998435435345",
      "dateOfBirth": "30/12/1996",
      "id": "10zddfgfd"
    },
    {
      "firstName": "Ira cvbvcbc dfgfdg",
      "lastName": "Lat name 8",
      "email": "fcvbcvbcvbcvdsfsdf@gmail.com",
      "phone": "+998435435345",
      "dateOfBirth": "30/12/1996",
      "id": "10234324"
    },
    {
      "firstName": "dsfsd",
      "lastName": "dsf sdf",
      "email": "sdfsdfsdf@gmail.com",
      "phone": "+380934444444",
      "dateOfBirth": "01/01/1992",
      "id": "nbaur8y"
    },
    {
      "firstName": "Test modal",
      "lastName": "last test",
      "email": "testerdddsfs@gmail.com",
      "phone": "+380934543545",
      "dateOfBirth": "02/01/2021",
      "id": "F6HXeeB"
    },
    {
      "firstName": "Hfdsgdfgdf",
      "lastName": "Ldfgdfgdf",
      "email": "dsfsdfsdf@gmail.com",
      "phone": "+380934534534",
      "dateOfBirth": "02/01/2021",
      "id": "OUBRp_S"
    },
    {
      "firstName": "New user f",
      "lastName": "new User T",
      "email": "dsfsdfds@gmail.com",
      "phone": "+380564654654",
      "dateOfBirth": "02/01/2021",
      "id": "H-PxPDv"
    },
    {
      "firstName": "Ndsfsdfsd",
      "lastName": "Hdsfdsfsdfsd",
      "email": "sdfsdfsdfsdfsd@gmail.com",
      "phone": "+380564654645",
      "dateOfBirth": "02/01/2021",
      "id": "y61fG78"
    },
    {
      "firstName": "Htretretert",
      "lastName": "Lsdfsdfsdf",
      "email": "sdfsdfsdfsd@gmail.com",
      "phone": "+380546546546",
      "dateOfBirth": "02/01/2021",
      "id": "DtsT0CV"
    },
    {
      "firstName": "Hsdf gfdgdfgdf",
      "lastName": "dfg dfgdfgd",
      "email": "dfgfdgdfgdf@gmail.com",
      "phone": "+380345345345",
      "dateOfBirth": "02/01/2021",
      "id": "FHaAU9P"
    },
    {
      "firstName": "Ghjgjghjghj",
      "lastName": "fghfghfghfghf",
      "email": "fghfghfghfgh@gmail.com",
      "phone": "+380435435345",
      "dateOfBirth": "02/01/2021",
      "id": "MHUmTn-"
    },
    {
      "firstName": "Ksdfsdfsdf",
      "lastName": "LKdsffsdfsd",
      "email": "sadasdas@gmail.com",
      "phone": "+380534654654",
      "dateOfBirth": "02/01/2021",
      "id": "gy0422Q"
    },
    {
      "firstName": "dsfsdfsdfs",
      "lastName": "fdfsdfsdfsdf",
      "email": "sdfsdfsdfsdf@gmail.com",
      "phone": "+380435345435",
      "dateOfBirth": "02/01/2021",
      "id": "gyzw6zH"
    },
    {
      "firstName": "sdfsdfsd",
      "lastName": "fsdfsdfvcsd",
      "email": "dsfsdfsdfsd@gmail.com",
      "phone": "+380345435435",
      "dateOfBirth": "02/01/2021",
      "id": "Dt1al1R"
    },
    {
      "firstName": "Aleretksandr",
      "lastName": "Kuzmefdgnko",
      "email": "sashatest@gmail.com",
      "phone": "+380456456456",
      "dateOfBirth": "08/01/1997",
      "id": "dsdddghjyj"
    },
    {
      "firstName": "Aleksfdg andr",
      "lastName": "Kuzmertenko",
      "email": "ewrewrwe@gmail.com",
      "phone": "+380456456456",
      "dateOfBirth": "08/01/1997",
      "id": "rggdvbfh"
    },
    {
      "firstName": "Alekertsandr",
      "lastName": "Kuzmefdgnko",
      "email": "ghfghfg@gmail.com",
      "phone": "+380456456456",
      "dateOfBirth": "08/01/1997",
      "id": "dfgdfgertyyrth"
    },
    {
      "firstName": "Alekd fgsandr",
      "lastName": "Kuzretmenko",
      "email": "ertertert@gmail.com",
      "phone": "+380456456456",
      "dateOfBirth": "08/01/1997",
      "id": "bghjghdgh"
    },
    {
      "firstName": "Alekfdg sandr",
      "lastName": "Kuzme fdgnko",
      "email": "zcxvzcxv@gmail.com",
      "phone": "+380456456456",
      "dateOfBirth": "08/01/1997",
      "id": "vdfyhnfgfgf"
    },
    {
      "firstName": "Aleksdf gandr",
      "lastName": "Kuzmfdg enko",
      "email": "retertfg@gmail.com",
      "phone": "+380456456456",
      "dateOfBirth": "08/01/1997",
      "id": "fghytrhhnmhg"
    },
    {
      "firstName": "Aleksfd gandr",
      "lastName": "Kuzmfd genko",
      "email": "zcvcxvxcz@gmail.com",
      "phone": "+380456456456",
      "dateOfBirth": "08/01/1997",
      "id": "xcvcnbtyy"
    },
    {
      "firstName": "Aleksandr",
      "lastName": "Kuzmenko",
      "email": "cvbvcbcv@gmail.com",
      "phone": "+380456456456",
      "dateOfBirth": "08/01/1997",
      "id": "iopkyuiky"
    },
    {
      "firstName": "Alekfd gdfsandr",
      "lastName": "Kuzmedf gnko",
      "email": "dfgerter@gmail.com",
      "phone": "+380456456456",
      "dateOfBirth": "08/01/1997",
      "id": "sdhytytynn"
    },
    {
      "firstName": "Alek vcsandr",
      "lastName": "Kuzmenko",
      "email": "sasfdsghatbvcest@gmail.com",
      "phone": "+380456456456",
      "dateOfBirth": "08/01/1997",
      "id": "bgfbgfbbg"
    },
    {
      "firstName": "Aleksre tandr",
      "lastName": "Kuzmenko",
      "email": "dfgsfdgsdf@gmail.com",
      "phone": "+380456456456",
      "dateOfBirth": "08/01/1997",
      "id": "wwerrvdvdfg"
    },
    {
      "firstName": "Aleksret erandr",
      "lastName": "Kuzmenko",
      "email": "fdsadfsdf@gmail.com",
      "phone": "+380456456456",
      "dateOfBirth": "08/01/1997",
      "id": "ccvdfdsd"
    },
    {
      "firstName": "Alekdfgdsandr",
      "lastName": "Kuzmenko",
      "email": "sashatdfgdfgdfest@gmail.com",
      "phone": "+380456456456",
      "dateOfBirth": "08/01/1997",
      "id": "oiujjjj"
    },
    {
      "firstName": "Aleksfdg dfandr",
      "lastName": "Kuzmenko",
      "email": "sashavcbvcbtest@gmail.com",
      "phone": "+380456456456",
      "dateOfBirth": "08/01/1997",
      "id": "adsghhghj"
    },
    {
      "firstName": "Alekdf gsandr",
      "lastName": "Kuzmenko",
      "email": "sashreteratest@gmail.com",
      "phone": "+380456456456",
      "dateOfBirth": "08/01/1997",
      "id": "wwwsdfdc"
    },
    {
      "firstName": "Ale cvbcvksandr",
      "lastName": "Kuzmenko",
      "email": "saasdfsdshatest@gmail.com",
      "phone": "+380456456456",
      "dateOfBirth": "08/01/1997",
      "id": "mmmhfhf"
    },
    {
      "firstName": "Ale fdgdf ksandr",
      "lastName": "Kuzmenko",
      "email": "sashdfgfdatest@gmail.com",
      "phone": "+380456456456",
      "dateOfBirth": "08/01/1997",
      "id": "ertrtttt"
    },
    {
      "firstName": "Aleksretreandr",
      "lastName": "Kuzmenko",
      "email": "sashadfsgfdgdf@gmail.com",
      "phone": "+380456456456",
      "dateOfBirth": "08/01/1997",
      "id": "kiiigghjytj"
    },
    {
      "firstName": "Aledfgdfksandr",
      "lastName": "Kuzmenko",
      "email": "cvbcvxb@gmail.com",
      "phone": "+380456456456",
      "dateOfBirth": "08/01/1997",
      "id": "aaawwvfg"
    },
    {
      "firstName": "Aledhg  dfksandr",
      "lastName": "Kuzmenko",
      "email": "ssfdgsdf@gmail.com",
      "phone": "+380456456456",
      "dateOfBirth": "08/01/1997",
      "id": "cvcerjkjf"
    },
    {
      "firstName": "Alekfg h fgsandr",
      "lastName": "Kuzmenko",
      "email": "dfggdfgdf@gmail.com",
      "phone": "+380456456456",
      "dateOfBirth": "08/01/1997",
      "id": "lkliuiu"
    },
    {
      "firstName": "Aleksf ghfg andr",
      "lastName": "Kuzmenko",
      "email": "dgdfgdst@gmail.com",
      "phone": "+380456456456",
      "dateOfBirth": "08/01/1997",
      "id": "asdsdfgdf"
    },
    {
      "firstName": "Aleksa fghfgndr",
      "lastName": "Kuzmenko",
      "email": "sbcbcvbcest@gmail.com",
      "phone": "+380456456456",
      "dateOfBirth": "08/01/1997",
      "id": "iuoui"
    },
    {
      "firstName": "Alekgf hfg hsandr",
      "lastName": "Kuzmenko",
      "email": "fdgfdgtest@gmail.com",
      "phone": "+380456456456",
      "dateOfBirth": "08/01/1997",
      "id": "mrtytrmgkgk"
    },
    {
      "firstName": "Aleksgf hfg handr",
      "lastName": "Kuzmenko",
      "email": "sashadfgdfg@gmail.com",
      "phone": "+380456456456",
      "dateOfBirth": "08/01/1997",
      "id": "mdfmgkgk"
    },
    {
      "firstName": "tyty",
      "lastName": "tytyt",
      "email": "tytry@gmail.com",
      "phone": "+380454545",
      "dateOfBirth": "03/01/2021",
      "card": "",
      "id": "1OJTmHe"
    },
    {
      "firstName": "Newuser",
      "lastName": "Lastname",
      "email": "tesfft@gmail.com",
      "phone": "+380666666666",
      "dateOfBirth": "03/01/1992",
      "card": "",
      "id": "680o8Hm"
    },
    {
      "firstName": "Last test user",
      "lastName": "Jdsdsd",
      "email": "asdasdasd@gmail.com",
      "phone": "+380435345345",
      "dateOfBirth": "11/01/1989",
      "card": "",
      "id": "HcwkS6s"
    }
  ]
}